[{"id":"6f765b09.3bf9f4","type":"tab","label":"Flow 3","disabled":false,"info":""},{"id":"887e77ff.bd2a6","type":"inject","z":"6f765b09.3bf9f4","name":"Sintel","props":[{"p":"payload"}],"repeat":"","crontab":"","once":false,"onceDelay":0.1,"topic":"","payload":"https://commondatastorage.googleapis.com/gtv-videos-bucket/CastVideos/hls/Sintel.m3u8","payloadType":"str","x":136,"y":157,"wires":[["a45a8a11.1a4458"]]},{"id":"a45a8a11.1a4458","type":"ui_mp4frag","z":"6f765b09.3bf9f4","name":"","group":"8a0ad045.8329c","order":3,"width":"6","height":4,"readyPoster":"https://raw.githubusercontent.com/kevinGodell/node-red-contrib-ui-mp4frag/master/video_playback_ready.png","errorPoster":"https://raw.githubusercontent.com/kevinGodell/node-red-contrib-ui-mp4frag/master/video_playback_error.png","hlsJsConfig":"{\"liveDurationInfinity\":true,\"liveBackBufferLength\":0,\"maxBufferLength\":5,\"manifestLoadingTimeOut\":1000,\"manifestLoadingMaxRetry\":10,\"manifestLoadingRetryDelay\":500}","restart":"true","autoplay":"true","x":481,"y":156,"wires":[[]]},{"id":"a59caaa8.0aa278","type":"inject","z":"6f765b09.3bf9f4","name":"Elephants Dream","props":[{"p":"payload"}],"repeat":"","crontab":"","once":false,"onceDelay":0.1,"topic":"","payload":"https://commondatastorage.googleapis.com/gtv-videos-bucket/CastVideos/hls/ElephantsDream.m3u8","payloadType":"str","x":165,"y":216,"wires":[["a45a8a11.1a4458"]]},{"id":"53d7683c.fd1118","type":"inject","z":"6f765b09.3bf9f4","name":"Big Buck Bunny","props":[{"p":"payload"}],"repeat":"","crontab":"","once":false,"onceDelay":0.1,"topic":"","payload":"https://commondatastorage.googleapis.com/gtv-videos-bucket/CastVideos/hls/BigBuckBunny.m3u8","payloadType":"str","x":166,"y":97,"wires":[["a45a8a11.1a4458"]]},{"id":"8a0ad045.8329c","type":"ui_group","z":"","name":"","tab":"4e54a2ca.371c7c","order":1,"disp":false,"width":"6","collapse":false},{"id":"4e54a2ca.371c7c","type":"ui_tab","z":"","name":"video test","icon":"dashboard","disabled":false,"hidden":false}]